LICENSE
MANIFEST.in
README.md
requirements.txt
setup.py
django_monaco_editor/__init__.py
django_monaco_editor/fields.py
django_monaco_editor/models.py
django_monaco_editor/settings.py
django_monaco_editor/widgets.py
django_monaco_editor.egg-info/PKG-INFO
django_monaco_editor.egg-info/SOURCES.txt
django_monaco_editor.egg-info/dependency_links.txt
django_monaco_editor.egg-info/requires.txt
django_monaco_editor.egg-info/top_level.txt
django_monaco_editor/static/django_monaco_editor/css/editor.css
django_monaco_editor/static/django_monaco_editor/js/editor.js
django_monaco_editor/static/external/css/github-markdown.css
django_monaco_editor/static/external/js/marked.min.js
django_monaco_editor/static/external/monaco-editor/CHANGELOG.md
django_monaco_editor/static/external/monaco-editor/LICENSE
django_monaco_editor/static/external/monaco-editor/README.md
django_monaco_editor/static/external/monaco-editor/ThirdPartyNotices.txt
django_monaco_editor/static/external/monaco-editor/monaco.d.ts
django_monaco_editor/static/external/monaco-editor/package.json
django_monaco_editor/static/external/monaco-editor/dev/bundleInfo.json
django_monaco_editor/static/external/monaco-editor/dev/nls.metadata.json
django_monaco_editor/static/external/monaco-editor/dev/vs/loader.js
django_monaco_editor/static/external/monaco-editor/dev/vs/loader.js.map
django_monaco_editor/static/external/monaco-editor/dev/vs/base/browser/ui/codiconLabel/codicon/codicon.ttf
django_monaco_editor/static/external/monaco-editor/dev/vs/base/worker/workerMain.js
django_monaco_editor/static/external/monaco-editor/dev/vs/base/worker/workerMain.js.map
django_monaco_editor/static/external/monaco-editor/dev/vs/basic-languages/_.contribution.js
django_monaco_editor/static/external/monaco-editor/dev/vs/basic-languages/abap/abap.contribution.js
django_monaco_editor/static/external/monaco-editor/dev/vs/basic-languages/abap/abap.js
django_monaco_editor/static/external/monaco-editor/dev/vs/basic-languages/apex/apex.contribution.js
django_monaco_editor/static/external/monaco-editor/dev/vs/basic-languages/apex/apex.js
django_monaco_editor/static/external/monaco-editor/dev/vs/basic-languages/azcli/azcli.contribution.js
